{"file":"blog/2022-11-21-deephaven-functions.md","objects":{"unique_heartrates":{"type":"Table","data":{"columns":[{"name":"HeartRate","type":"int"}],"rows":[[{"value":"119"}],[{"value":"120"}],[{"value":"118"}],[{"value":"121"}],[{"value":"122"}],[{"value":"123"}],[{"value":"124"}],[{"value":"125"}],[{"value":"126"}],[{"value":"127"}],[{"value":"128"}],[{"value":"129"}],[{"value":"130"}],[{"value":"131"}],[{"value":"132"}],[{"value":"133"}],[{"value":"134"}],[{"value":"135"}],[{"value":"136"}],[{"value":"137"}],[{"value":"138"}],[{"value":"139"}],[{"value":"140"}],[{"value":"141"}],[{"value":"142"}],[{"value":"143"}],[{"value":"144"}],[{"value":"145"}],[{"value":"146"}],[{"value":"147"}],[{"value":"148"}],[{"value":"149"}],[{"value":"150"}],[{"value":"151"}],[{"value":"152"}],[{"value":"153"}],[{"value":"154"}],[{"value":"155"}],[{"value":"156"}],[{"value":"117"}]]}},"unique_heartrate_cadences":{"type":"Table","data":{"columns":[{"name":"HeartRate","type":"int"},{"name":"Cadence","type":"int"}],"rows":[[{"value":"119"},{"value":"32"}],[{"value":"120"},{"value":"45"}],[{"value":"120"},{"value":"56"}],[{"value":"120"},{"value":"44"}],[{"value":"120"},{"value":"42"}],[{"value":"119"},{"value":"42"}],[{"value":"119"},{"value":"43"}],[{"value":"119"},{"value":"44"}],[{"value":"119"},{"value":"46"}],[{"value":"119"},{"value":"48"}],[{"value":"120"},{"value":"61"}],[{"value":"120"},{"value":"51"}],[{"value":"120"},{"value":"35"}],[{"value":"119"},{"value":"45"}],[{"value":"119"},{"value":"40"}],[{"value":"119"},{"value":"36"}],[{"value":"119"},{"value":"35"}],[{"value":"119"},{"value":"37"}],[{"value":"118"},{"value":"47"}],[{"value":"118"},{"value":"38"}],[{"value":"119"},{"value":"50"}],[{"value":"119"},{"value":"33"}],[{"value":"120"},{"value":"31"}],[{"value":"120"},{"value":"70"}],[{"value":"120"},{"value":"77"}],[{"value":"120"},{"value":"80"}],[{"value":"120"},{"value":"81"}],[{"value":"120"},{"value":"78"}],[{"value":"120"},{"value":"67"}],[{"value":"119"},{"value":"52"}],[{"value":"120"},{"value":"46"}],[{"value":"120"},{"value":"69"}],[{"value":"120"},{"value":"76"}],[{"value":"120"},{"value":"79"}],[{"value":"121"},{"value":"84"}],[{"value":"121"},{"value":"83"}],[{"value":"122"},{"value":"85"}],[{"value":"123"},{"value":"96"}],[{"value":"123"},{"value":"97"}],[{"value":"124"},{"value":"97"}],[{"value":"124"},{"value":"92"}],[{"value":"124"},{"value":"95"}],[{"value":"125"},{"value":"95"}],[{"value":"126"},{"value":"95"}],[{"value":"126"},{"value":"92"}],[{"value":"126"},{"value":"89"}],[{"value":"127"},{"value":"75"}],[{"value":"127"},{"value":"65"}],[{"value":"127"},{"value":"51"}],[{"value":"128"},{"value":"44"}],[{"value":"128"},{"value":"48"}],[{"value":"128"},{"value":"49"}],[{"value":"128"},{"value":"41"}],[{"value":"129"},{"value":"33"}],[{"value":"129"},{"value":"44"}],[{"value":"129"},{"value":"0"}],[{"value":"129"},{"value":"26"}],[{"value":"130"},{"value":"34"}],[{"value":"130"},{"value":"22"}],[{"value":"130"},{"value":"18"}],[{"value":"130"},{"value":"43"}],[{"value":"131"},{"value":"43"}],[{"value":"131"},{"value":"0"}],[{"value":"131"},{"value":"23"}],[{"value":"131"},{"value":"17"}],[{"value":"132"},{"value":"17"}],[{"value":"132"},{"value":"43"}],[{"value":"132"},{"value":"60"}],[{"value":"132"},{"value":"65"}],[{"value":"132"},{"value":"71"}],[{"value":"132"},{"value":"84"}],[{"value":"132"},{"value":"98"}],[{"value":"132"},{"value":"99"}],[{"value":"132"},{"value":"96"}],[{"value":"132"},{"value":"94"}],[{"value":"133"},{"value":"91"}],[{"value":"133"},{"value":"92"}],[{"value":"134"},{"value":"91"}],[{"value":"134"},{"value":"92"}],[{"value":"135"},{"value":"91"}],[{"value":"135"},{"value":"97"}],[{"value":"136"},{"value":"97"}],[{"value":"136"},{"value":"89"}],[{"value":"136"},{"value":"90"}],[{"value":"136"},{"value":"86"}],[{"value":"136"},{"value":"87"}],[{"value":"137"},{"value":"87"}],[{"value":"137"},{"value":"55"}],[{"value":"137"},{"value":"53"}],[{"value":"137"},{"value":"52"}],[{"value":"137"},{"value":"59"}],[{"value":"138"},{"value":"52"}],[{"value":"138"},{"value":"56"}],[{"value":"137"},{"value":"56"}],[{"value":"138"},{"value":"38"}],[{"value":"137"},{"value":"33"}],[{"value":"137"},{"value":"51"}],[{"value":"137"},{"value":"58"}],[{"value":"136"},{"value":"67"}],[{"value":"136"},{"value":"72"}]]}}}}