{"file":"core/docs/reference/table-operations/update-by-operations/ema-time.md","objects":{"source":{"type":"Table","data":{"columns":[{"name":"Timestamp","type":"java.time.Instant"},{"name":"Letter","type":"java.lang.String"},{"name":"X","type":"int"}],"rows":[[{"value":"1682913600000000000"},{"value":"A"},{"value":"12"}],[{"value":"1682913601000000000"},{"value":"B"},{"value":"6"}],[{"value":"1682913602000000000"},{"value":"A"},{"value":"23"}],[{"value":"1682913603000000000"},{"value":"B"},{"value":"11"}],[{"value":"1682913604000000000"},{"value":"A"},{"value":"24"}],[{"value":"1682913605000000000"},{"value":"B"},{"value":"9"}],[{"value":"1682913606000000000"},{"value":"A"},{"value":"7"}],[{"value":"1682913607000000000"},{"value":"B"},{"value":"10"}],[{"value":"1682913608000000000"},{"value":"A"},{"value":"4"}],[{"value":"1682913609000000000"},{"value":"B"},{"value":"21"}],[{"value":"1682913610000000000"},{"value":"A"},{"value":"22"}],[{"value":"1682913611000000000"},{"value":"B"},{"value":"3"}],[{"value":"1682913612000000000"},{"value":"A"},{"value":"15"}],[{"value":"1682913613000000000"},{"value":"B"},{"value":"14"}],[{"value":"1682913614000000000"},{"value":"A"},{"value":"13"}],[{"value":"1682913615000000000"},{"value":"B"},{"value":"18"}],[{"value":"1682913616000000000"},{"value":"A"},{"value":"17"}],[{"value":"1682913617000000000"},{"value":"B"},{"value":"8"}],[{"value":"1682913618000000000"},{"value":"A"},{"value":"3"}],[{"value":"1682913619000000000"},{"value":"B"},{"value":"5"}],[{"value":"1682913620000000000"},{"value":"A"},{"value":"9"}],[{"value":"1682913621000000000"},{"value":"B"},{"value":"13"}],[{"value":"1682913622000000000"},{"value":"A"},{"value":"21"}],[{"value":"1682913623000000000"},{"value":"B"},{"value":"8"}],[{"value":"1682913624000000000"},{"value":"A"},{"value":"21"}],[{"value":"1682913625000000000"},{"value":"B"},{"value":"3"}],[{"value":"1682913626000000000"},{"value":"A"},{"value":"23"}],[{"value":"1682913627000000000"},{"value":"B"},{"value":"3"}],[{"value":"1682913628000000000"},{"value":"A"},{"value":"6"}],[{"value":"1682913629000000000"},{"value":"B"},{"value":"16"}],[{"value":"1682913630000000000"},{"value":"A"},{"value":"8"}],[{"value":"1682913631000000000"},{"value":"B"},{"value":"12"}],[{"value":"1682913632000000000"},{"value":"A"},{"value":"12"}],[{"value":"1682913633000000000"},{"value":"B"},{"value":"0"}],[{"value":"1682913634000000000"},{"value":"A"},{"value":"0"}],[{"value":"1682913635000000000"},{"value":"B"},{"value":"19"}],[{"value":"1682913636000000000"},{"value":"A"},{"value":"12"}],[{"value":"1682913637000000000"},{"value":"B"},{"value":"19"}],[{"value":"1682913638000000000"},{"value":"A"},{"value":"16"}],[{"value":"1682913639000000000"},{"value":"B"},{"value":"1"}],[{"value":"1682913640000000000"},{"value":"A"},{"value":"10"}],[{"value":"1682913641000000000"},{"value":"B"},{"value":"2"}],[{"value":"1682913642000000000"},{"value":"A"},{"value":"22"}],[{"value":"1682913643000000000"},{"value":"B"},{"value":"6"}],[{"value":"1682913644000000000"},{"value":"A"},{"value":"3"}],[{"value":"1682913645000000000"},{"value":"B"},{"value":"0"}],[{"value":"1682913646000000000"},{"value":"A"},{"value":"21"}],[{"value":"1682913647000000000"},{"value":"B"},{"value":"5"}],[{"value":"1682913648000000000"},{"value":"A"},{"value":"7"}],[{"value":"1682913649000000000"},{"value":"B"},{"value":"16"}],[{"value":"1682913650000000000"},{"value":"A"},{"value":"20"}],[{"value":"1682913651000000000"},{"value":"B"},{"value":"4"}],[{"value":"1682913652000000000"},{"value":"A"},{"value":"1"}],[{"value":"1682913653000000000"},{"value":"B"},{"value":"7"}],[{"value":"1682913654000000000"},{"value":"A"},{"value":"12"}],[{"value":"1682913655000000000"},{"value":"B"},{"value":"11"}],[{"value":"1682913656000000000"},{"value":"A"},{"value":"24"}],[{"value":"1682913657000000000"},{"value":"B"},{"value":"0"}],[{"value":"1682913658000000000"},{"value":"A"},{"value":"19"}],[{"value":"1682913659000000000"},{"value":"B"},{"value":"3"}]]}},"result":{"type":"Table","data":{"columns":[{"name":"Timestamp","type":"java.time.Instant"},{"name":"Letter","type":"java.lang.String"},{"name":"X","type":"int"},{"name":"EmaX","type":"double"}],"rows":[[{"value":"1682913600000000000"},{"value":"A"},{"value":"12"},{"value":"12.0000"}],[{"value":"1682913601000000000"},{"value":"B"},{"value":"6"},{"value":"10.9124"}],[{"value":"1682913602000000000"},{"value":"A"},{"value":"23"},{"value":"13.1035"}],[{"value":"1682913603000000000"},{"value":"B"},{"value":"11"},{"value":"12.7222"}],[{"value":"1682913604000000000"},{"value":"A"},{"value":"24"},{"value":"14.7665"}],[{"value":"1682913605000000000"},{"value":"B"},{"value":"9"},{"value":"13.7212"}],[{"value":"1682913606000000000"},{"value":"A"},{"value":"7"},{"value":"12.5029"}],[{"value":"1682913607000000000"},{"value":"B"},{"value":"10"},{"value":"12.0492"}],[{"value":"1682913608000000000"},{"value":"A"},{"value":"4"},{"value":"10.5901"}],[{"value":"1682913609000000000"},{"value":"B"},{"value":"21"},{"value":"12.4771"}],[{"value":"1682913610000000000"},{"value":"A"},{"value":"22"},{"value":"14.2033"}],[{"value":"1682913611000000000"},{"value":"B"},{"value":"3"},{"value":"12.1725"}],[{"value":"1682913612000000000"},{"value":"A"},{"value":"15"},{"value":"12.6850"}],[{"value":"1682913613000000000"},{"value":"B"},{"value":"14"},{"value":"12.9234"}],[{"value":"1682913614000000000"},{"value":"A"},{"value":"13"},{"value":"12.9373"}],[{"value":"1682913615000000000"},{"value":"B"},{"value":"18"},{"value":"13.8550"}],[{"value":"1682913616000000000"},{"value":"A"},{"value":"17"},{"value":"14.4251"}],[{"value":"1682913617000000000"},{"value":"B"},{"value":"8"},{"value":"13.2604"}],[{"value":"1682913618000000000"},{"value":"A"},{"value":"3"},{"value":"11.4005"}],[{"value":"1682913619000000000"},{"value":"B"},{"value":"5"},{"value":"10.2403"}],[{"value":"1682913620000000000"},{"value":"A"},{"value":"9"},{"value":"10.0155"}],[{"value":"1682913621000000000"},{"value":"B"},{"value":"13"},{"value":"10.5565"}],[{"value":"1682913622000000000"},{"value":"A"},{"value":"21"},{"value":"12.4496"}],[{"value":"1682913623000000000"},{"value":"B"},{"value":"8"},{"value":"11.6430"}],[{"value":"1682913624000000000"},{"value":"A"},{"value":"21"},{"value":"13.3391"}],[{"value":"1682913625000000000"},{"value":"B"},{"value":"3"},{"value":"11.4650"}],[{"value":"1682913626000000000"},{"value":"A"},{"value":"23"},{"value":"13.5559"}],[{"value":"1682913627000000000"},{"value":"B"},{"value":"3"},{"value":"11.6425"}],[{"value":"1682913628000000000"},{"value":"A"},{"value":"6"},{"value":"10.6196"}],[{"value":"1682913629000000000"},{"value":"B"},{"value":"16"},{"value":"11.5949"}],[{"value":"1682913630000000000"},{"value":"A"},{"value":"8"},{"value":"10.9433"}],[{"value":"1682913631000000000"},{"value":"B"},{"value":"12"},{"value":"11.1348"}],[{"value":"1682913632000000000"},{"value":"A"},{"value":"12"},{"value":"11.2917"}],[{"value":"1682913633000000000"},{"value":"B"},{"value":"0"},{"value":"9.2448"}],[{"value":"1682913634000000000"},{"value":"A"},{"value":"0"},{"value":"7.5690"}],[{"value":"1682913635000000000"},{"value":"B"},{"value":"19"},{"value":"9.6411"}],[{"value":"1682913636000000000"},{"value":"A"},{"value":"12"},{"value":"10.0687"}],[{"value":"1682913637000000000"},{"value":"B"},{"value":"19"},{"value":"11.6877"}],[{"value":"1682913638000000000"},{"value":"A"},{"value":"16"},{"value":"12.4694"}],[{"value":"1682913639000000000"},{"value":"B"},{"value":"1"},{"value":"10.3903"}],[{"value":"1682913640000000000"},{"value":"A"},{"value":"10"},{"value":"10.3196"}],[{"value":"1682913641000000000"},{"value":"B"},{"value":"2"},{"value":"8.8115"}],[{"value":"1682913642000000000"},{"value":"A"},{"value":"22"},{"value":"11.2022"}],[{"value":"1682913643000000000"},{"value":"B"},{"value":"6"},{"value":"10.2592"}],[{"value":"1682913644000000000"},{"value":"A"},{"value":"3"},{"value":"8.9433"}],[{"value":"1682913645000000000"},{"value":"B"},{"value":"0"},{"value":"7.3222"}],[{"value":"1682913646000000000"},{"value":"A"},{"value":"21"},{"value":"9.8015"}],[{"value":"1682913647000000000"},{"value":"B"},{"value":"5"},{"value":"8.9312"}],[{"value":"1682913648000000000"},{"value":"A"},{"value":"7"},{"value":"8.5811"}],[{"value":"1682913649000000000"},{"value":"B"},{"value":"16"},{"value":"9.9259"}],[{"value":"1682913650000000000"},{"value":"A"},{"value":"20"},{"value":"11.7520"}],[{"value":"1682913651000000000"},{"value":"B"},{"value":"4"},{"value":"10.3468"}],[{"value":"1682913652000000000"},{"value":"A"},{"value":"1"},{"value":"8.6525"}],[{"value":"1682913653000000000"},{"value":"B"},{"value":"7"},{"value":"8.3530"}],[{"value":"1682913654000000000"},{"value":"A"},{"value":"12"},{"value":"9.0141"}],[{"value":"1682913655000000000"},{"value":"B"},{"value":"11"},{"value":"9.3741"}],[{"value":"1682913656000000000"},{"value":"A"},{"value":"24"},{"value":"12.0253"}],[{"value":"1682913657000000000"},{"value":"B"},{"value":"0"},{"value":"9.8455"}],[{"value":"1682913658000000000"},{"value":"A"},{"value":"19"},{"value":"11.5049"}],[{"value":"1682913659000000000"},{"value":"B"},{"value":"3"},{"value":"9.9632"}]]}}}}