{"file":"core/docs/reference/cheat-sheets/cheat-sheet.md","objects":{"copy1":{"type":"Table","data":{"columns":[{"name":"X","type":"long"},{"name":"Double1","type":"double"},{"name":"Int1","type":"int"},{"name":"Timestamp","type":"java.time.Instant"},{"name":"Date","type":"java.lang.String"},{"name":"String1","type":"java.lang.String"},{"name":"String2","type":"java.lang.String"}],"rows":[[{"value":"0"},{"value":"94.3023"},{"value":"5"},{"value":"1451628000000000000"},{"value":"2016-01-01T06:00:00Z"},{"value":"R"},{"value":"abS"}],[{"value":"1"},{"value":"8.6729"},{"value":"43"},{"value":"1451631600000000000"},{"value":"2016-01-01T07:00:00Z"},{"value":"R"},{"value":"p"}],[{"value":"2"},{"value":"3.0752"},{"value":"73"},{"value":"1451635200000000000"},{"value":"2016-01-01T08:00:00Z"},{"value":"X"},{"value":"Mn"}],[{"value":"3"},{"value":"44.1703"},{"value":"20"},{"value":"1451638800000000000"},{"value":"2016-01-01T09:00:00Z"},{"value":"O"},{"value":"G"}],[{"value":"4"},{"value":"80.3311"},{"value":"34"},{"value":"1451642400000000000"},{"value":"2016-01-01T10:00:00Z"},{"value":"W"},{"value":"ybJ"}],[{"value":"5"},{"value":"83.5215"},{"value":"35"},{"value":"1451646000000000000"},{"value":"2016-01-01T11:00:00Z"},{"value":"M"},{"value":"cUZ"}],[{"value":"6"},{"value":"91.0089"},{"value":"3"},{"value":"1451649600000000000"},{"value":"2016-01-01T12:00:00Z"},{"value":"K"},{"value":"D"}],[{"value":"7"},{"value":"60.8868"},{"value":"25"},{"value":"1451653200000000000"},{"value":"2016-01-01T13:00:00Z"},{"value":"X"},{"value":"YsF"}],[{"value":"8"},{"value":"72.9197"},{"value":"93"},{"value":"1451656800000000000"},{"value":"2016-01-01T14:00:00Z"},{"value":"O"},{"value":"vVY"}],[{"value":"9"},{"value":"49.7076"},{"value":"37"},{"value":"1451660400000000000"},{"value":"2016-01-01T15:00:00Z"},{"value":"I"},{"value":"Eh"}],[{"value":"10"},{"value":"31.0900"},{"value":"56"},{"value":"1451664000000000000"},{"value":"2016-01-01T16:00:00Z"},{"value":"L"},{"value":"d"}],[{"value":"11"},{"value":"88.8044"},{"value":"68"},{"value":"1451667600000000000"},{"value":"2016-01-01T17:00:00Z"},{"value":"O"},{"value":"s"}],[{"value":"12"},{"value":"70.4239"},{"value":"59"},{"value":"1451671200000000000"},{"value":"2016-01-01T18:00:00Z"},{"value":"V"},{"value":"yfj"}],[{"value":"13"},{"value":"11.1450"},{"value":"21"},{"value":"1451674800000000000"},{"value":"2016-01-01T19:00:00Z"},{"value":"V"},{"value":"i"}],[{"value":"14"},{"value":"78.7962"},{"value":"38"},{"value":"1451678400000000000"},{"value":"2016-01-01T20:00:00Z"},{"value":"D"},{"value":"d"}],[{"value":"15"},{"value":"41.7921"},{"value":"2"},{"value":"1451682000000000000"},{"value":"2016-01-01T21:00:00Z"},{"value":"V"},{"value":"I"}],[{"value":"16"},{"value":"72.0296"},{"value":"58"},{"value":"1451685600000000000"},{"value":"2016-01-01T22:00:00Z"},{"value":"V"},{"value":"uqy"}],[{"value":"17"},{"value":"29.1955"},{"value":"72"},{"value":"1451689200000000000"},{"value":"2016-01-01T23:00:00Z"},{"value":"G"},{"value":"m"}],[{"value":"18"},{"value":"38.6866"},{"value":"68"},{"value":"1451692800000000000"},{"value":"2016-01-02T00:00:00Z"},{"value":"I"},{"value":"OWx"}],[{"value":"19"},{"value":"56.5346"},{"value":"86"},{"value":"1451696400000000000"},{"value":"2016-01-02T01:00:00Z"},{"value":"Q"},{"value":"oi"}],[{"value":"20"},{"value":"12.8632"},{"value":"85"},{"value":"1451700000000000000"},{"value":"2016-01-02T02:00:00Z"},{"value":"F"},{"value":"nL"}],[{"value":"21"},{"value":"64.4800"},{"value":"92"},{"value":"1451703600000000000"},{"value":"2016-01-02T03:00:00Z"},{"value":"W"},{"value":"FBc"}],[{"value":"22"},{"value":"4.9967"},{"value":"26"},{"value":"1451707200000000000"},{"value":"2016-01-02T04:00:00Z"},{"value":"O"},{"value":"oE"}],[{"value":"23"},{"value":"4.0285"},{"value":"85"},{"value":"1451710800000000000"},{"value":"2016-01-02T05:00:00Z"},{"value":"U"},{"value":"Ggn"}],[{"value":"24"},{"value":"55.6945"},{"value":"77"},{"value":"1451714400000000000"},{"value":"2016-01-02T06:00:00Z"},{"value":"W"},{"value":"L"}],[{"value":"25"},{"value":"18.5245"},{"value":"27"},{"value":"1451718000000000000"},{"value":"2016-01-02T07:00:00Z"},{"value":"A"},{"value":"vm"}],[{"value":"26"},{"value":"74.1697"},{"value":"7"},{"value":"1451721600000000000"},{"value":"2016-01-02T08:00:00Z"},{"value":"Q"},{"value":"C"}],[{"value":"27"},{"value":"76.2326"},{"value":"87"},{"value":"1451725200000000000"},{"value":"2016-01-02T09:00:00Z"},{"value":"X"},{"value":"d"}],[{"value":"28"},{"value":"5.8149"},{"value":"46"},{"value":"1451728800000000000"},{"value":"2016-01-02T10:00:00Z"},{"value":"G"},{"value":"sGp"}],[{"value":"29"},{"value":"59.7708"},{"value":"79"},{"value":"1451732400000000000"},{"value":"2016-01-02T11:00:00Z"},{"value":"S"},{"value":"H"}],[{"value":"30"},{"value":"1.3098"},{"value":"24"},{"value":"1451736000000000000"},{"value":"2016-01-02T12:00:00Z"},{"value":"I"},{"value":"W"}],[{"value":"31"},{"value":"73.1071"},{"value":"31"},{"value":"1451739600000000000"},{"value":"2016-01-02T13:00:00Z"},{"value":"S"},{"value":"QV"}],[{"value":"32"},{"value":"96.1779"},{"value":"57"},{"value":"1451743200000000000"},{"value":"2016-01-02T14:00:00Z"},{"value":"L"},{"value":"pI"}],[{"value":"33"},{"value":"45.9676"},{"value":"54"},{"value":"1451746800000000000"},{"value":"2016-01-02T15:00:00Z"},{"value":"P"},{"value":"x"}],[{"value":"34"},{"value":"29.9457"},{"value":"15"},{"value":"1451750400000000000"},{"value":"2016-01-02T16:00:00Z"},{"value":"B"},{"value":"C"}],[{"value":"35"},{"value":"31.5004"},{"value":"33"},{"value":"1451754000000000000"},{"value":"2016-01-02T17:00:00Z"},{"value":"O"},{"value":"R"}],[{"value":"36"},{"value":"16.8760"},{"value":"14"},{"value":"1451757600000000000"},{"value":"2016-01-02T18:00:00Z"},{"value":"Y"},{"value":"P"}],[{"value":"37"},{"value":"81.3750"},{"value":"24"},{"value":"1451761200000000000"},{"value":"2016-01-02T19:00:00Z"},{"value":"B"},{"value":"oxD"}],[{"value":"38"},{"value":"81.0823"},{"value":"44"},{"value":"1451764800000000000"},{"value":"2016-01-02T20:00:00Z"},{"value":"Q"},{"value":"e"}],[{"value":"39"},{"value":"28.8942"},{"value":"6"},{"value":"1451768400000000000"},{"value":"2016-01-02T21:00:00Z"},{"value":"M"},{"value":"zmu"}],[{"value":"40"},{"value":"81.2352"},{"value":"99"},{"value":"1451772000000000000"},{"value":"2016-01-02T22:00:00Z"},{"value":"F"},{"value":"sf"}],[{"value":"41"},{"value":"97.4425"},{"value":"75"},{"value":"1451775600000000000"},{"value":"2016-01-02T23:00:00Z"},{"value":"W"},{"value":"GN"}],[{"value":"42"},{"value":"87.9144"},{"value":"34"},{"value":"1451779200000000000"},{"value":"2016-01-03T00:00:00Z"},{"value":"P"},{"value":"G"}],[{"value":"43"},{"value":"38.6702"},{"value":"31"},{"value":"1451782800000000000"},{"value":"2016-01-03T01:00:00Z"},{"value":"A"},{"value":"cU"}],[{"value":"44"},{"value":"89.3909"},{"value":"53"},{"value":"1451786400000000000"},{"value":"2016-01-03T02:00:00Z"},{"value":"V"},{"value":"W"}],[{"value":"45"},{"value":"94.4151"},{"value":"62"},{"value":"1451790000000000000"},{"value":"2016-01-03T03:00:00Z"},{"value":"L"},{"value":"fTJ"}],[{"value":"46"},{"value":"43.1369"},{"value":"59"},{"value":"1451793600000000000"},{"value":"2016-01-03T04:00:00Z"},{"value":"W"},{"value":"Sew"}],[{"value":"47"},{"value":"81.8003"},{"value":"80"},{"value":"1451797200000000000"},{"value":"2016-01-03T05:00:00Z"},{"value":"N"},{"value":"X"}],[{"value":"48"},{"value":"67.0636"},{"value":"72"},{"value":"1451800800000000000"},{"value":"2016-01-03T06:00:00Z"},{"value":"U"},{"value":"eh"}],[{"value":"49"},{"value":"41.4953"},{"value":"57"},{"value":"1451804400000000000"},{"value":"2016-01-03T07:00:00Z"},{"value":"N"},{"value":"O"}],[{"value":"50"},{"value":"6.5734"},{"value":"4"},{"value":"1451808000000000000"},{"value":"2016-01-03T08:00:00Z"},{"value":"V"},{"value":"xF"}],[{"value":"51"},{"value":"25.5833"},{"value":"10"},{"value":"1451811600000000000"},{"value":"2016-01-03T09:00:00Z"},{"value":"D"},{"value":"rQ"}],[{"value":"52"},{"value":"83.1676"},{"value":"29"},{"value":"1451815200000000000"},{"value":"2016-01-03T10:00:00Z"},{"value":"K"},{"value":"DO"}],[{"value":"53"},{"value":"25.9827"},{"value":"12"},{"value":"1451818800000000000"},{"value":"2016-01-03T11:00:00Z"},{"value":"Q"},{"value":"w"}],[{"value":"54"},{"value":"47.9417"},{"value":"46"},{"value":"1451822400000000000"},{"value":"2016-01-03T12:00:00Z"},{"value":"K"},{"value":"wSe"}],[{"value":"55"},{"value":"78.8652"},{"value":"4"},{"value":"1451826000000000000"},{"value":"2016-01-03T13:00:00Z"},{"value":"A"},{"value":"GG"}],[{"value":"56"},{"value":"53.3112"},{"value":"19"},{"value":"1451829600000000000"},{"value":"2016-01-03T14:00:00Z"},{"value":"Q"},{"value":"kD"}],[{"value":"57"},{"value":"64.7036"},{"value":"73"},{"value":"1451833200000000000"},{"value":"2016-01-03T15:00:00Z"},{"value":"U"},{"value":"vBi"}],[{"value":"58"},{"value":"36.2208"},{"value":"55"},{"value":"1451836800000000000"},{"value":"2016-01-03T16:00:00Z"},{"value":"H"},{"value":"Q"}],[{"value":"59"},{"value":"92.6337"},{"value":"14"},{"value":"1451840400000000000"},{"value":"2016-01-03T17:00:00Z"},{"value":"U"},{"value":"CgQ"}],[{"value":"60"},{"value":"86.7286"},{"value":"33"},{"value":"1451844000000000000"},{"value":"2016-01-03T18:00:00Z"},{"value":"B"},{"value":"D"}],[{"value":"61"},{"value":"67.2259"},{"value":"1"},{"value":"1451847600000000000"},{"value":"2016-01-03T19:00:00Z"},{"value":"H"},{"value":"jw"}],[{"value":"62"},{"value":"89.9085"},{"value":"33"},{"value":"1451851200000000000"},{"value":"2016-01-03T20:00:00Z"},{"value":"T"},{"value":"ahq"}],[{"value":"63"},{"value":"71.1204"},{"value":"71"},{"value":"1451854800000000000"},{"value":"2016-01-03T21:00:00Z"},{"value":"Q"},{"value":"K"}],[{"value":"64"},{"value":"17.5087"},{"value":"20"},{"value":"1451858400000000000"},{"value":"2016-01-03T22:00:00Z"},{"value":"S"},{"value":"WSU"}],[{"value":"65"},{"value":"64.1116"},{"value":"93"},{"value":"1451862000000000000"},{"value":"2016-01-03T23:00:00Z"},{"value":"X"},{"value":"EYY"}],[{"value":"66"},{"value":"12.3790"},{"value":"75"},{"value":"1451865600000000000"},{"value":"2016-01-04T00:00:00Z"},{"value":"U"},{"value":"Tx"}],[{"value":"67"},{"value":"58.1168"},{"value":"76"},{"value":"1451869200000000000"},{"value":"2016-01-04T01:00:00Z"},{"value":"D"},{"value":"J"}],[{"value":"68"},{"value":"50.5198"},{"value":"44"},{"value":"1451872800000000000"},{"value":"2016-01-04T02:00:00Z"},{"value":"P"},{"value":"gB"}],[{"value":"69"},{"value":"38.7195"},{"value":"62"},{"value":"1451876400000000000"},{"value":"2016-01-04T03:00:00Z"},{"value":"V"},{"value":"Suu"}],[{"value":"70"},{"value":"48.2538"},{"value":"87"},{"value":"1451880000000000000"},{"value":"2016-01-04T04:00:00Z"},{"value":"F"},{"value":"YHs"}],[{"value":"71"},{"value":"17.9660"},{"value":"51"},{"value":"1451883600000000000"},{"value":"2016-01-04T05:00:00Z"},{"value":"E"},{"value":"YbJ"}],[{"value":"72"},{"value":"29.3064"},{"value":"39"},{"value":"1451887200000000000"},{"value":"2016-01-04T06:00:00Z"},{"value":"K"},{"value":"eh"}],[{"value":"73"},{"value":"48.6911"},{"value":"4"},{"value":"1451890800000000000"},{"value":"2016-01-04T07:00:00Z"},{"value":"M"},{"value":"cNu"}],[{"value":"74"},{"value":"83.0085"},{"value":"11"},{"value":"1451894400000000000"},{"value":"2016-01-04T08:00:00Z"},{"value":"I"},{"value":"ao"}],[{"value":"75"},{"value":"46.6007"},{"value":"30"},{"value":"1451898000000000000"},{"value":"2016-01-04T09:00:00Z"},{"value":"U"},{"value":"I"}],[{"value":"76"},{"value":"76.9140"},{"value":"41"},{"value":"1451901600000000000"},{"value":"2016-01-04T10:00:00Z"},{"value":"X"},{"value":"idM"}],[{"value":"77"},{"value":"97.5797"},{"value":"56"},{"value":"1451905200000000000"},{"value":"2016-01-04T11:00:00Z"},{"value":"Y"},{"value":"B"}],[{"value":"78"},{"value":"47.9275"},{"value":"48"},{"value":"1451908800000000000"},{"value":"2016-01-04T12:00:00Z"},{"value":"N"},{"value":"N"}],[{"value":"79"},{"value":"56.8320"},{"value":"62"},{"value":"1451912400000000000"},{"value":"2016-01-04T13:00:00Z"},{"value":"P"},{"value":"NOh"}],[{"value":"80"},{"value":"65.7962"},{"value":"86"},{"value":"1451916000000000000"},{"value":"2016-01-04T14:00:00Z"},{"value":"U"},{"value":"ztA"}],[{"value":"81"},{"value":"83.0671"},{"value":"33"},{"value":"1451919600000000000"},{"value":"2016-01-04T15:00:00Z"},{"value":"Q"},{"value":"C"}],[{"value":"82"},{"value":"77.7487"},{"value":"8"},{"value":"1451923200000000000"},{"value":"2016-01-04T16:00:00Z"},{"value":"N"},{"value":"vUw"}],[{"value":"83"},{"value":"12.3114"},{"value":"36"},{"value":"1451926800000000000"},{"value":"2016-01-04T17:00:00Z"},{"value":"V"},{"value":"CW"}],[{"value":"84"},{"value":"64.5875"},{"value":"88"},{"value":"1451930400000000000"},{"value":"2016-01-04T18:00:00Z"},{"value":"O"},{"value":"HPK"}],[{"value":"85"},{"value":"66.0047"},{"value":"28"},{"value":"1451934000000000000"},{"value":"2016-01-04T19:00:00Z"},{"value":"U"},{"value":"jRN"}],[{"value":"86"},{"value":"93.1710"},{"value":"4"},{"value":"1451937600000000000"},{"value":"2016-01-04T20:00:00Z"},{"value":"T"},{"value":"D"}],[{"value":"87"},{"value":"99.7433"},{"value":"68"},{"value":"1451941200000000000"},{"value":"2016-01-04T21:00:00Z"},{"value":"V"},{"value":"Uv"}],[{"value":"88"},{"value":"22.3954"},{"value":"70"},{"value":"1451944800000000000"},{"value":"2016-01-04T22:00:00Z"},{"value":"J"},{"value":"QM"}],[{"value":"89"},{"value":"43.8974"},{"value":"95"},{"value":"1451948400000000000"},{"value":"2016-01-04T23:00:00Z"},{"value":"P"},{"value":"odf"}],[{"value":"90"},{"value":"49.9070"},{"value":"92"},{"value":"1451952000000000000"},{"value":"2016-01-05T00:00:00Z"},{"value":"V"},{"value":"Vz"}],[{"value":"91"},{"value":"1.9320"},{"value":"18"},{"value":"1451955600000000000"},{"value":"2016-01-05T01:00:00Z"},{"value":"U"},{"value":"p"}],[{"value":"92"},{"value":"76.0557"},{"value":"62"},{"value":"1451959200000000000"},{"value":"2016-01-05T02:00:00Z"},{"value":"R"},{"value":"gfs"}],[{"value":"93"},{"value":"85.2456"},{"value":"84"},{"value":"1451962800000000000"},{"value":"2016-01-05T03:00:00Z"},{"value":"I"},{"value":"cJ"}],[{"value":"94"},{"value":"46.3058"},{"value":"59"},{"value":"1451966400000000000"},{"value":"2016-01-05T04:00:00Z"},{"value":"X"},{"value":"Du"}],[{"value":"95"},{"value":"16.8200"},{"value":"41"},{"value":"1451970000000000000"},{"value":"2016-01-05T05:00:00Z"},{"value":"V"},{"value":"nJl"}],[{"value":"96"},{"value":"76.0096"},{"value":"51"},{"value":"1451973600000000000"},{"value":"2016-01-05T06:00:00Z"},{"value":"G"},{"value":"NL"}],[{"value":"97"},{"value":"52.1305"},{"value":"12"},{"value":"1451977200000000000"},{"value":"2016-01-05T07:00:00Z"},{"value":"O"},{"value":"RQ"}],[{"value":"98"},{"value":"93.5746"},{"value":"94"},{"value":"1451980800000000000"},{"value":"2016-01-05T08:00:00Z"},{"value":"A"},{"value":"G"}],[{"value":"99"},{"value":"77.5067"},{"value":"33"},{"value":"1451984400000000000"},{"value":"2016-01-05T09:00:00Z"},{"value":"O"},{"value":"DND"}]]}},"merge_same_static":{"type":"Table","data":{"columns":[{"name":"X","type":"long"},{"name":"Double1","type":"double"},{"name":"Int1","type":"int"},{"name":"Timestamp","type":"java.time.Instant"},{"name":"Date","type":"java.lang.String"},{"name":"String1","type":"java.lang.String"},{"name":"String2","type":"java.lang.String"}],"rows":[[{"value":"0"},{"value":"94.3023"},{"value":"5"},{"value":"1451628000000000000"},{"value":"2016-01-01T06:00:00Z"},{"value":"R"},{"value":"abS"}],[{"value":"1"},{"value":"8.6729"},{"value":"43"},{"value":"1451631600000000000"},{"value":"2016-01-01T07:00:00Z"},{"value":"R"},{"value":"p"}],[{"value":"2"},{"value":"3.0752"},{"value":"73"},{"value":"1451635200000000000"},{"value":"2016-01-01T08:00:00Z"},{"value":"X"},{"value":"Mn"}],[{"value":"3"},{"value":"44.1703"},{"value":"20"},{"value":"1451638800000000000"},{"value":"2016-01-01T09:00:00Z"},{"value":"O"},{"value":"G"}],[{"value":"4"},{"value":"80.3311"},{"value":"34"},{"value":"1451642400000000000"},{"value":"2016-01-01T10:00:00Z"},{"value":"W"},{"value":"ybJ"}],[{"value":"5"},{"value":"83.5215"},{"value":"35"},{"value":"1451646000000000000"},{"value":"2016-01-01T11:00:00Z"},{"value":"M"},{"value":"cUZ"}],[{"value":"6"},{"value":"91.0089"},{"value":"3"},{"value":"1451649600000000000"},{"value":"2016-01-01T12:00:00Z"},{"value":"K"},{"value":"D"}],[{"value":"7"},{"value":"60.8868"},{"value":"25"},{"value":"1451653200000000000"},{"value":"2016-01-01T13:00:00Z"},{"value":"X"},{"value":"YsF"}],[{"value":"8"},{"value":"72.9197"},{"value":"93"},{"value":"1451656800000000000"},{"value":"2016-01-01T14:00:00Z"},{"value":"O"},{"value":"vVY"}],[{"value":"9"},{"value":"49.7076"},{"value":"37"},{"value":"1451660400000000000"},{"value":"2016-01-01T15:00:00Z"},{"value":"I"},{"value":"Eh"}],[{"value":"10"},{"value":"31.0900"},{"value":"56"},{"value":"1451664000000000000"},{"value":"2016-01-01T16:00:00Z"},{"value":"L"},{"value":"d"}],[{"value":"11"},{"value":"88.8044"},{"value":"68"},{"value":"1451667600000000000"},{"value":"2016-01-01T17:00:00Z"},{"value":"O"},{"value":"s"}],[{"value":"12"},{"value":"70.4239"},{"value":"59"},{"value":"1451671200000000000"},{"value":"2016-01-01T18:00:00Z"},{"value":"V"},{"value":"yfj"}],[{"value":"13"},{"value":"11.1450"},{"value":"21"},{"value":"1451674800000000000"},{"value":"2016-01-01T19:00:00Z"},{"value":"V"},{"value":"i"}],[{"value":"14"},{"value":"78.7962"},{"value":"38"},{"value":"1451678400000000000"},{"value":"2016-01-01T20:00:00Z"},{"value":"D"},{"value":"d"}],[{"value":"15"},{"value":"41.7921"},{"value":"2"},{"value":"1451682000000000000"},{"value":"2016-01-01T21:00:00Z"},{"value":"V"},{"value":"I"}],[{"value":"16"},{"value":"72.0296"},{"value":"58"},{"value":"1451685600000000000"},{"value":"2016-01-01T22:00:00Z"},{"value":"V"},{"value":"uqy"}],[{"value":"17"},{"value":"29.1955"},{"value":"72"},{"value":"1451689200000000000"},{"value":"2016-01-01T23:00:00Z"},{"value":"G"},{"value":"m"}],[{"value":"18"},{"value":"38.6866"},{"value":"68"},{"value":"1451692800000000000"},{"value":"2016-01-02T00:00:00Z"},{"value":"I"},{"value":"OWx"}],[{"value":"19"},{"value":"56.5346"},{"value":"86"},{"value":"1451696400000000000"},{"value":"2016-01-02T01:00:00Z"},{"value":"Q"},{"value":"oi"}],[{"value":"20"},{"value":"12.8632"},{"value":"85"},{"value":"1451700000000000000"},{"value":"2016-01-02T02:00:00Z"},{"value":"F"},{"value":"nL"}],[{"value":"21"},{"value":"64.4800"},{"value":"92"},{"value":"1451703600000000000"},{"value":"2016-01-02T03:00:00Z"},{"value":"W"},{"value":"FBc"}],[{"value":"22"},{"value":"4.9967"},{"value":"26"},{"value":"1451707200000000000"},{"value":"2016-01-02T04:00:00Z"},{"value":"O"},{"value":"oE"}],[{"value":"23"},{"value":"4.0285"},{"value":"85"},{"value":"1451710800000000000"},{"value":"2016-01-02T05:00:00Z"},{"value":"U"},{"value":"Ggn"}],[{"value":"24"},{"value":"55.6945"},{"value":"77"},{"value":"1451714400000000000"},{"value":"2016-01-02T06:00:00Z"},{"value":"W"},{"value":"L"}],[{"value":"25"},{"value":"18.5245"},{"value":"27"},{"value":"1451718000000000000"},{"value":"2016-01-02T07:00:00Z"},{"value":"A"},{"value":"vm"}],[{"value":"26"},{"value":"74.1697"},{"value":"7"},{"value":"1451721600000000000"},{"value":"2016-01-02T08:00:00Z"},{"value":"Q"},{"value":"C"}],[{"value":"27"},{"value":"76.2326"},{"value":"87"},{"value":"1451725200000000000"},{"value":"2016-01-02T09:00:00Z"},{"value":"X"},{"value":"d"}],[{"value":"28"},{"value":"5.8149"},{"value":"46"},{"value":"1451728800000000000"},{"value":"2016-01-02T10:00:00Z"},{"value":"G"},{"value":"sGp"}],[{"value":"29"},{"value":"59.7708"},{"value":"79"},{"value":"1451732400000000000"},{"value":"2016-01-02T11:00:00Z"},{"value":"S"},{"value":"H"}],[{"value":"30"},{"value":"1.3098"},{"value":"24"},{"value":"1451736000000000000"},{"value":"2016-01-02T12:00:00Z"},{"value":"I"},{"value":"W"}],[{"value":"31"},{"value":"73.1071"},{"value":"31"},{"value":"1451739600000000000"},{"value":"2016-01-02T13:00:00Z"},{"value":"S"},{"value":"QV"}],[{"value":"32"},{"value":"96.1779"},{"value":"57"},{"value":"1451743200000000000"},{"value":"2016-01-02T14:00:00Z"},{"value":"L"},{"value":"pI"}],[{"value":"33"},{"value":"45.9676"},{"value":"54"},{"value":"1451746800000000000"},{"value":"2016-01-02T15:00:00Z"},{"value":"P"},{"value":"x"}],[{"value":"34"},{"value":"29.9457"},{"value":"15"},{"value":"1451750400000000000"},{"value":"2016-01-02T16:00:00Z"},{"value":"B"},{"value":"C"}],[{"value":"35"},{"value":"31.5004"},{"value":"33"},{"value":"1451754000000000000"},{"value":"2016-01-02T17:00:00Z"},{"value":"O"},{"value":"R"}],[{"value":"36"},{"value":"16.8760"},{"value":"14"},{"value":"1451757600000000000"},{"value":"2016-01-02T18:00:00Z"},{"value":"Y"},{"value":"P"}],[{"value":"37"},{"value":"81.3750"},{"value":"24"},{"value":"1451761200000000000"},{"value":"2016-01-02T19:00:00Z"},{"value":"B"},{"value":"oxD"}],[{"value":"38"},{"value":"81.0823"},{"value":"44"},{"value":"1451764800000000000"},{"value":"2016-01-02T20:00:00Z"},{"value":"Q"},{"value":"e"}],[{"value":"39"},{"value":"28.8942"},{"value":"6"},{"value":"1451768400000000000"},{"value":"2016-01-02T21:00:00Z"},{"value":"M"},{"value":"zmu"}],[{"value":"40"},{"value":"81.2352"},{"value":"99"},{"value":"1451772000000000000"},{"value":"2016-01-02T22:00:00Z"},{"value":"F"},{"value":"sf"}],[{"value":"41"},{"value":"97.4425"},{"value":"75"},{"value":"1451775600000000000"},{"value":"2016-01-02T23:00:00Z"},{"value":"W"},{"value":"GN"}],[{"value":"42"},{"value":"87.9144"},{"value":"34"},{"value":"1451779200000000000"},{"value":"2016-01-03T00:00:00Z"},{"value":"P"},{"value":"G"}],[{"value":"43"},{"value":"38.6702"},{"value":"31"},{"value":"1451782800000000000"},{"value":"2016-01-03T01:00:00Z"},{"value":"A"},{"value":"cU"}],[{"value":"44"},{"value":"89.3909"},{"value":"53"},{"value":"1451786400000000000"},{"value":"2016-01-03T02:00:00Z"},{"value":"V"},{"value":"W"}],[{"value":"45"},{"value":"94.4151"},{"value":"62"},{"value":"1451790000000000000"},{"value":"2016-01-03T03:00:00Z"},{"value":"L"},{"value":"fTJ"}],[{"value":"46"},{"value":"43.1369"},{"value":"59"},{"value":"1451793600000000000"},{"value":"2016-01-03T04:00:00Z"},{"value":"W"},{"value":"Sew"}],[{"value":"47"},{"value":"81.8003"},{"value":"80"},{"value":"1451797200000000000"},{"value":"2016-01-03T05:00:00Z"},{"value":"N"},{"value":"X"}],[{"value":"48"},{"value":"67.0636"},{"value":"72"},{"value":"1451800800000000000"},{"value":"2016-01-03T06:00:00Z"},{"value":"U"},{"value":"eh"}],[{"value":"49"},{"value":"41.4953"},{"value":"57"},{"value":"1451804400000000000"},{"value":"2016-01-03T07:00:00Z"},{"value":"N"},{"value":"O"}],[{"value":"50"},{"value":"6.5734"},{"value":"4"},{"value":"1451808000000000000"},{"value":"2016-01-03T08:00:00Z"},{"value":"V"},{"value":"xF"}],[{"value":"51"},{"value":"25.5833"},{"value":"10"},{"value":"1451811600000000000"},{"value":"2016-01-03T09:00:00Z"},{"value":"D"},{"value":"rQ"}],[{"value":"52"},{"value":"83.1676"},{"value":"29"},{"value":"1451815200000000000"},{"value":"2016-01-03T10:00:00Z"},{"value":"K"},{"value":"DO"}],[{"value":"53"},{"value":"25.9827"},{"value":"12"},{"value":"1451818800000000000"},{"value":"2016-01-03T11:00:00Z"},{"value":"Q"},{"value":"w"}],[{"value":"54"},{"value":"47.9417"},{"value":"46"},{"value":"1451822400000000000"},{"value":"2016-01-03T12:00:00Z"},{"value":"K"},{"value":"wSe"}],[{"value":"55"},{"value":"78.8652"},{"value":"4"},{"value":"1451826000000000000"},{"value":"2016-01-03T13:00:00Z"},{"value":"A"},{"value":"GG"}],[{"value":"56"},{"value":"53.3112"},{"value":"19"},{"value":"1451829600000000000"},{"value":"2016-01-03T14:00:00Z"},{"value":"Q"},{"value":"kD"}],[{"value":"57"},{"value":"64.7036"},{"value":"73"},{"value":"1451833200000000000"},{"value":"2016-01-03T15:00:00Z"},{"value":"U"},{"value":"vBi"}],[{"value":"58"},{"value":"36.2208"},{"value":"55"},{"value":"1451836800000000000"},{"value":"2016-01-03T16:00:00Z"},{"value":"H"},{"value":"Q"}],[{"value":"59"},{"value":"92.6337"},{"value":"14"},{"value":"1451840400000000000"},{"value":"2016-01-03T17:00:00Z"},{"value":"U"},{"value":"CgQ"}],[{"value":"60"},{"value":"86.7286"},{"value":"33"},{"value":"1451844000000000000"},{"value":"2016-01-03T18:00:00Z"},{"value":"B"},{"value":"D"}],[{"value":"61"},{"value":"67.2259"},{"value":"1"},{"value":"1451847600000000000"},{"value":"2016-01-03T19:00:00Z"},{"value":"H"},{"value":"jw"}],[{"value":"62"},{"value":"89.9085"},{"value":"33"},{"value":"1451851200000000000"},{"value":"2016-01-03T20:00:00Z"},{"value":"T"},{"value":"ahq"}],[{"value":"63"},{"value":"71.1204"},{"value":"71"},{"value":"1451854800000000000"},{"value":"2016-01-03T21:00:00Z"},{"value":"Q"},{"value":"K"}],[{"value":"64"},{"value":"17.5087"},{"value":"20"},{"value":"1451858400000000000"},{"value":"2016-01-03T22:00:00Z"},{"value":"S"},{"value":"WSU"}],[{"value":"65"},{"value":"64.1116"},{"value":"93"},{"value":"1451862000000000000"},{"value":"2016-01-03T23:00:00Z"},{"value":"X"},{"value":"EYY"}],[{"value":"66"},{"value":"12.3790"},{"value":"75"},{"value":"1451865600000000000"},{"value":"2016-01-04T00:00:00Z"},{"value":"U"},{"value":"Tx"}],[{"value":"67"},{"value":"58.1168"},{"value":"76"},{"value":"1451869200000000000"},{"value":"2016-01-04T01:00:00Z"},{"value":"D"},{"value":"J"}],[{"value":"68"},{"value":"50.5198"},{"value":"44"},{"value":"1451872800000000000"},{"value":"2016-01-04T02:00:00Z"},{"value":"P"},{"value":"gB"}],[{"value":"69"},{"value":"38.7195"},{"value":"62"},{"value":"1451876400000000000"},{"value":"2016-01-04T03:00:00Z"},{"value":"V"},{"value":"Suu"}],[{"value":"70"},{"value":"48.2538"},{"value":"87"},{"value":"1451880000000000000"},{"value":"2016-01-04T04:00:00Z"},{"value":"F"},{"value":"YHs"}],[{"value":"71"},{"value":"17.9660"},{"value":"51"},{"value":"1451883600000000000"},{"value":"2016-01-04T05:00:00Z"},{"value":"E"},{"value":"YbJ"}],[{"value":"72"},{"value":"29.3064"},{"value":"39"},{"value":"1451887200000000000"},{"value":"2016-01-04T06:00:00Z"},{"value":"K"},{"value":"eh"}],[{"value":"73"},{"value":"48.6911"},{"value":"4"},{"value":"1451890800000000000"},{"value":"2016-01-04T07:00:00Z"},{"value":"M"},{"value":"cNu"}],[{"value":"74"},{"value":"83.0085"},{"value":"11"},{"value":"1451894400000000000"},{"value":"2016-01-04T08:00:00Z"},{"value":"I"},{"value":"ao"}],[{"value":"75"},{"value":"46.6007"},{"value":"30"},{"value":"1451898000000000000"},{"value":"2016-01-04T09:00:00Z"},{"value":"U"},{"value":"I"}],[{"value":"76"},{"value":"76.9140"},{"value":"41"},{"value":"1451901600000000000"},{"value":"2016-01-04T10:00:00Z"},{"value":"X"},{"value":"idM"}],[{"value":"77"},{"value":"97.5797"},{"value":"56"},{"value":"1451905200000000000"},{"value":"2016-01-04T11:00:00Z"},{"value":"Y"},{"value":"B"}],[{"value":"78"},{"value":"47.9275"},{"value":"48"},{"value":"1451908800000000000"},{"value":"2016-01-04T12:00:00Z"},{"value":"N"},{"value":"N"}],[{"value":"79"},{"value":"56.8320"},{"value":"62"},{"value":"1451912400000000000"},{"value":"2016-01-04T13:00:00Z"},{"value":"P"},{"value":"NOh"}],[{"value":"80"},{"value":"65.7962"},{"value":"86"},{"value":"1451916000000000000"},{"value":"2016-01-04T14:00:00Z"},{"value":"U"},{"value":"ztA"}],[{"value":"81"},{"value":"83.0671"},{"value":"33"},{"value":"1451919600000000000"},{"value":"2016-01-04T15:00:00Z"},{"value":"Q"},{"value":"C"}],[{"value":"82"},{"value":"77.7487"},{"value":"8"},{"value":"1451923200000000000"},{"value":"2016-01-04T16:00:00Z"},{"value":"N"},{"value":"vUw"}],[{"value":"83"},{"value":"12.3114"},{"value":"36"},{"value":"1451926800000000000"},{"value":"2016-01-04T17:00:00Z"},{"value":"V"},{"value":"CW"}],[{"value":"84"},{"value":"64.5875"},{"value":"88"},{"value":"1451930400000000000"},{"value":"2016-01-04T18:00:00Z"},{"value":"O"},{"value":"HPK"}],[{"value":"85"},{"value":"66.0047"},{"value":"28"},{"value":"1451934000000000000"},{"value":"2016-01-04T19:00:00Z"},{"value":"U"},{"value":"jRN"}],[{"value":"86"},{"value":"93.1710"},{"value":"4"},{"value":"1451937600000000000"},{"value":"2016-01-04T20:00:00Z"},{"value":"T"},{"value":"D"}],[{"value":"87"},{"value":"99.7433"},{"value":"68"},{"value":"1451941200000000000"},{"value":"2016-01-04T21:00:00Z"},{"value":"V"},{"value":"Uv"}],[{"value":"88"},{"value":"22.3954"},{"value":"70"},{"value":"1451944800000000000"},{"value":"2016-01-04T22:00:00Z"},{"value":"J"},{"value":"QM"}],[{"value":"89"},{"value":"43.8974"},{"value":"95"},{"value":"1451948400000000000"},{"value":"2016-01-04T23:00:00Z"},{"value":"P"},{"value":"odf"}],[{"value":"90"},{"value":"49.9070"},{"value":"92"},{"value":"1451952000000000000"},{"value":"2016-01-05T00:00:00Z"},{"value":"V"},{"value":"Vz"}],[{"value":"91"},{"value":"1.9320"},{"value":"18"},{"value":"1451955600000000000"},{"value":"2016-01-05T01:00:00Z"},{"value":"U"},{"value":"p"}],[{"value":"92"},{"value":"76.0557"},{"value":"62"},{"value":"1451959200000000000"},{"value":"2016-01-05T02:00:00Z"},{"value":"R"},{"value":"gfs"}],[{"value":"93"},{"value":"85.2456"},{"value":"84"},{"value":"1451962800000000000"},{"value":"2016-01-05T03:00:00Z"},{"value":"I"},{"value":"cJ"}],[{"value":"94"},{"value":"46.3058"},{"value":"59"},{"value":"1451966400000000000"},{"value":"2016-01-05T04:00:00Z"},{"value":"X"},{"value":"Du"}],[{"value":"95"},{"value":"16.8200"},{"value":"41"},{"value":"1451970000000000000"},{"value":"2016-01-05T05:00:00Z"},{"value":"V"},{"value":"nJl"}],[{"value":"96"},{"value":"76.0096"},{"value":"51"},{"value":"1451973600000000000"},{"value":"2016-01-05T06:00:00Z"},{"value":"G"},{"value":"NL"}],[{"value":"97"},{"value":"52.1305"},{"value":"12"},{"value":"1451977200000000000"},{"value":"2016-01-05T07:00:00Z"},{"value":"O"},{"value":"RQ"}],[{"value":"98"},{"value":"93.5746"},{"value":"94"},{"value":"1451980800000000000"},{"value":"2016-01-05T08:00:00Z"},{"value":"A"},{"value":"G"}],[{"value":"99"},{"value":"77.5067"},{"value":"33"},{"value":"1451984400000000000"},{"value":"2016-01-05T09:00:00Z"},{"value":"O"},{"value":"DND"}]]}},"copy_updating_1":{"type":"Table","data":{"columns":[{"name":"Timestamp","type":"java.time.Instant"},{"name":"X","type":"long"},{"name":"Double3","type":"double"},{"name":"Int3","type":"int"},{"name":"Date","type":"java.lang.String"},{"name":"String5","type":"java.lang.String"},{"name":"String6","type":"java.lang.String"}],"rows":[[{"value":"1694023119000000000"},{"value":"0"},{"value":"39.6270"},{"value":"93"},{"value":"2023-09-06T17:58:39Z"},{"value":"K"},{"value":"b"}]]}},"copy_updating_2":{"type":"Table","data":{"columns":[{"name":"Timestamp","type":"java.time.Instant"},{"name":"X","type":"long"},{"name":"Double3","type":"double"},{"name":"Int3","type":"int"},{"name":"Date","type":"java.lang.String"},{"name":"String5","type":"java.lang.String"},{"name":"String6","type":"java.lang.String"}],"rows":[[{"value":"1694023119000000000"},{"value":"0"},{"value":"39.6270"},{"value":"93"},{"value":"2023-09-06T17:58:39Z"},{"value":"K"},{"value":"b"}]]}},"merge_same_dynamic":{"type":"Table","data":{"columns":[{"name":"Timestamp","type":"java.time.Instant"},{"name":"X","type":"long"},{"name":"Double3","type":"double"},{"name":"Int3","type":"int"},{"name":"Date","type":"java.lang.String"},{"name":"String5","type":"java.lang.String"},{"name":"String6","type":"java.lang.String"}],"rows":[[{"value":"1694023119000000000"},{"value":"0"},{"value":"39.6270"},{"value":"93"},{"value":"2023-09-06T17:58:39Z"},{"value":"K"},{"value":"b"}],[{"value":"1694023119000000000"},{"value":"0"},{"value":"39.6270"},{"value":"93"},{"value":"2023-09-06T17:58:39Z"},{"value":"K"},{"value":"b"}]]}},"static_source_1v2":{"type":"Table","data":{"columns":[{"name":"Date","type":"java.lang.String"},{"name":"Timestamp","type":"java.time.Instant"},{"name":"SourceRowNum","type":"long"}],"rows":[[{"value":"2016-01-01T06:00:00Z"},{"value":"1451628000000000000"},{"value":"0"}],[{"value":"2016-01-01T07:00:00Z"},{"value":"1451631600000000000"},{"value":"1"}],[{"value":"2016-01-01T08:00:00Z"},{"value":"1451635200000000000"},{"value":"2"}],[{"value":"2016-01-01T09:00:00Z"},{"value":"1451638800000000000"},{"value":"3"}],[{"value":"2016-01-01T10:00:00Z"},{"value":"1451642400000000000"},{"value":"4"}],[{"value":"2016-01-01T11:00:00Z"},{"value":"1451646000000000000"},{"value":"5"}],[{"value":"2016-01-01T12:00:00Z"},{"value":"1451649600000000000"},{"value":"6"}],[{"value":"2016-01-01T13:00:00Z"},{"value":"1451653200000000000"},{"value":"7"}],[{"value":"2016-01-01T14:00:00Z"},{"value":"1451656800000000000"},{"value":"8"}],[{"value":"2016-01-01T15:00:00Z"},{"value":"1451660400000000000"},{"value":"9"}],[{"value":"2016-01-01T16:00:00Z"},{"value":"1451664000000000000"},{"value":"10"}],[{"value":"2016-01-01T17:00:00Z"},{"value":"1451667600000000000"},{"value":"11"}],[{"value":"2016-01-01T18:00:00Z"},{"value":"1451671200000000000"},{"value":"12"}],[{"value":"2016-01-01T19:00:00Z"},{"value":"1451674800000000000"},{"value":"13"}],[{"value":"2016-01-01T20:00:00Z"},{"value":"1451678400000000000"},{"value":"14"}],[{"value":"2016-01-01T21:00:00Z"},{"value":"1451682000000000000"},{"value":"15"}],[{"value":"2016-01-01T22:00:00Z"},{"value":"1451685600000000000"},{"value":"16"}],[{"value":"2016-01-01T23:00:00Z"},{"value":"1451689200000000000"},{"value":"17"}],[{"value":"2016-01-02T00:00:00Z"},{"value":"1451692800000000000"},{"value":"18"}],[{"value":"2016-01-02T01:00:00Z"},{"value":"1451696400000000000"},{"value":"19"}],[{"value":"2016-01-02T02:00:00Z"},{"value":"1451700000000000000"},{"value":"20"}],[{"value":"2016-01-02T03:00:00Z"},{"value":"1451703600000000000"},{"value":"21"}],[{"value":"2016-01-02T04:00:00Z"},{"value":"1451707200000000000"},{"value":"22"}],[{"value":"2016-01-02T05:00:00Z"},{"value":"1451710800000000000"},{"value":"23"}],[{"value":"2016-01-02T06:00:00Z"},{"value":"1451714400000000000"},{"value":"24"}],[{"value":"2016-01-02T07:00:00Z"},{"value":"1451718000000000000"},{"value":"25"}],[{"value":"2016-01-02T08:00:00Z"},{"value":"1451721600000000000"},{"value":"26"}],[{"value":"2016-01-02T09:00:00Z"},{"value":"1451725200000000000"},{"value":"27"}],[{"value":"2016-01-02T10:00:00Z"},{"value":"1451728800000000000"},{"value":"28"}],[{"value":"2016-01-02T11:00:00Z"},{"value":"1451732400000000000"},{"value":"29"}],[{"value":"2016-01-02T12:00:00Z"},{"value":"1451736000000000000"},{"value":"30"}],[{"value":"2016-01-02T13:00:00Z"},{"value":"1451739600000000000"},{"value":"31"}],[{"value":"2016-01-02T14:00:00Z"},{"value":"1451743200000000000"},{"value":"32"}],[{"value":"2016-01-02T15:00:00Z"},{"value":"1451746800000000000"},{"value":"33"}],[{"value":"2016-01-02T16:00:00Z"},{"value":"1451750400000000000"},{"value":"34"}],[{"value":"2016-01-02T17:00:00Z"},{"value":"1451754000000000000"},{"value":"35"}],[{"value":"2016-01-02T18:00:00Z"},{"value":"1451757600000000000"},{"value":"36"}],[{"value":"2016-01-02T19:00:00Z"},{"value":"1451761200000000000"},{"value":"37"}],[{"value":"2016-01-02T20:00:00Z"},{"value":"1451764800000000000"},{"value":"38"}],[{"value":"2016-01-02T21:00:00Z"},{"value":"1451768400000000000"},{"value":"39"}],[{"value":"2016-01-02T22:00:00Z"},{"value":"1451772000000000000"},{"value":"40"}],[{"value":"2016-01-02T23:00:00Z"},{"value":"1451775600000000000"},{"value":"41"}],[{"value":"2016-01-03T00:00:00Z"},{"value":"1451779200000000000"},{"value":"42"}],[{"value":"2016-01-03T01:00:00Z"},{"value":"1451782800000000000"},{"value":"43"}],[{"value":"2016-01-03T02:00:00Z"},{"value":"1451786400000000000"},{"value":"44"}],[{"value":"2016-01-03T03:00:00Z"},{"value":"1451790000000000000"},{"value":"45"}],[{"value":"2016-01-03T04:00:00Z"},{"value":"1451793600000000000"},{"value":"46"}],[{"value":"2016-01-03T05:00:00Z"},{"value":"1451797200000000000"},{"value":"47"}],[{"value":"2016-01-03T06:00:00Z"},{"value":"1451800800000000000"},{"value":"48"}],[{"value":"2016-01-03T07:00:00Z"},{"value":"1451804400000000000"},{"value":"49"}],[{"value":"2016-01-03T08:00:00Z"},{"value":"1451808000000000000"},{"value":"50"}],[{"value":"2016-01-03T09:00:00Z"},{"value":"1451811600000000000"},{"value":"51"}],[{"value":"2016-01-03T10:00:00Z"},{"value":"1451815200000000000"},{"value":"52"}],[{"value":"2016-01-03T11:00:00Z"},{"value":"1451818800000000000"},{"value":"53"}],[{"value":"2016-01-03T12:00:00Z"},{"value":"1451822400000000000"},{"value":"54"}],[{"value":"2016-01-03T13:00:00Z"},{"value":"1451826000000000000"},{"value":"55"}],[{"value":"2016-01-03T14:00:00Z"},{"value":"1451829600000000000"},{"value":"56"}],[{"value":"2016-01-03T15:00:00Z"},{"value":"1451833200000000000"},{"value":"57"}],[{"value":"2016-01-03T16:00:00Z"},{"value":"1451836800000000000"},{"value":"58"}],[{"value":"2016-01-03T17:00:00Z"},{"value":"1451840400000000000"},{"value":"59"}],[{"value":"2016-01-03T18:00:00Z"},{"value":"1451844000000000000"},{"value":"60"}],[{"value":"2016-01-03T19:00:00Z"},{"value":"1451847600000000000"},{"value":"61"}],[{"value":"2016-01-03T20:00:00Z"},{"value":"1451851200000000000"},{"value":"62"}],[{"value":"2016-01-03T21:00:00Z"},{"value":"1451854800000000000"},{"value":"63"}],[{"value":"2016-01-03T22:00:00Z"},{"value":"1451858400000000000"},{"value":"64"}],[{"value":"2016-01-03T23:00:00Z"},{"value":"1451862000000000000"},{"value":"65"}],[{"value":"2016-01-04T00:00:00Z"},{"value":"1451865600000000000"},{"value":"66"}],[{"value":"2016-01-04T01:00:00Z"},{"value":"1451869200000000000"},{"value":"67"}],[{"value":"2016-01-04T02:00:00Z"},{"value":"1451872800000000000"},{"value":"68"}],[{"value":"2016-01-04T03:00:00Z"},{"value":"1451876400000000000"},{"value":"69"}],[{"value":"2016-01-04T04:00:00Z"},{"value":"1451880000000000000"},{"value":"70"}],[{"value":"2016-01-04T05:00:00Z"},{"value":"1451883600000000000"},{"value":"71"}],[{"value":"2016-01-04T06:00:00Z"},{"value":"1451887200000000000"},{"value":"72"}],[{"value":"2016-01-04T07:00:00Z"},{"value":"1451890800000000000"},{"value":"73"}],[{"value":"2016-01-04T08:00:00Z"},{"value":"1451894400000000000"},{"value":"74"}],[{"value":"2016-01-04T09:00:00Z"},{"value":"1451898000000000000"},{"value":"75"}],[{"value":"2016-01-04T10:00:00Z"},{"value":"1451901600000000000"},{"value":"76"}],[{"value":"2016-01-04T11:00:00Z"},{"value":"1451905200000000000"},{"value":"77"}],[{"value":"2016-01-04T12:00:00Z"},{"value":"1451908800000000000"},{"value":"78"}],[{"value":"2016-01-04T13:00:00Z"},{"value":"1451912400000000000"},{"value":"79"}],[{"value":"2016-01-04T14:00:00Z"},{"value":"1451916000000000000"},{"value":"80"}],[{"value":"2016-01-04T15:00:00Z"},{"value":"1451919600000000000"},{"value":"81"}],[{"value":"2016-01-04T16:00:00Z"},{"value":"1451923200000000000"},{"value":"82"}],[{"value":"2016-01-04T17:00:00Z"},{"value":"1451926800000000000"},{"value":"83"}],[{"value":"2016-01-04T18:00:00Z"},{"value":"1451930400000000000"},{"value":"84"}],[{"value":"2016-01-04T19:00:00Z"},{"value":"1451934000000000000"},{"value":"85"}],[{"value":"2016-01-04T20:00:00Z"},{"value":"1451937600000000000"},{"value":"86"}],[{"value":"2016-01-04T21:00:00Z"},{"value":"1451941200000000000"},{"value":"87"}],[{"value":"2016-01-04T22:00:00Z"},{"value":"1451944800000000000"},{"value":"88"}],[{"value":"2016-01-04T23:00:00Z"},{"value":"1451948400000000000"},{"value":"89"}],[{"value":"2016-01-05T00:00:00Z"},{"value":"1451952000000000000"},{"value":"90"}],[{"value":"2016-01-05T01:00:00Z"},{"value":"1451955600000000000"},{"value":"91"}],[{"value":"2016-01-05T02:00:00Z"},{"value":"1451959200000000000"},{"value":"92"}],[{"value":"2016-01-05T03:00:00Z"},{"value":"1451962800000000000"},{"value":"93"}],[{"value":"2016-01-05T04:00:00Z"},{"value":"1451966400000000000"},{"value":"94"}],[{"value":"2016-01-05T05:00:00Z"},{"value":"1451970000000000000"},{"value":"95"}],[{"value":"2016-01-05T06:00:00Z"},{"value":"1451973600000000000"},{"value":"96"}],[{"value":"2016-01-05T07:00:00Z"},{"value":"1451977200000000000"},{"value":"97"}],[{"value":"2016-01-05T08:00:00Z"},{"value":"1451980800000000000"},{"value":"98"}],[{"value":"2016-01-05T09:00:00Z"},{"value":"1451984400000000000"},{"value":"99"}]]}},"ticking_source_v2":{"type":"Table","data":{"columns":[{"name":"Date","type":"java.lang.String"},{"name":"Timestamp","type":"java.time.Instant"},{"name":"SourceRowNum","type":"long"}],"rows":[[{"value":"2023-09-06T17:58:39Z"},{"value":"1694023119000000000"},{"value":"0"}]]}},"merge_static_and_dynamic":{"type":"Table","data":{"columns":[{"name":"Date","type":"java.lang.String"},{"name":"Timestamp","type":"java.time.Instant"},{"name":"SourceRowNum","type":"long"}],"rows":[[{"value":"2016-01-01T06:00:00Z"},{"value":"1451628000000000000"},{"value":"0"}],[{"value":"2016-01-01T07:00:00Z"},{"value":"1451631600000000000"},{"value":"1"}],[{"value":"2016-01-01T08:00:00Z"},{"value":"1451635200000000000"},{"value":"2"}],[{"value":"2016-01-01T09:00:00Z"},{"value":"1451638800000000000"},{"value":"3"}],[{"value":"2016-01-01T10:00:00Z"},{"value":"1451642400000000000"},{"value":"4"}],[{"value":"2016-01-01T11:00:00Z"},{"value":"1451646000000000000"},{"value":"5"}],[{"value":"2016-01-01T12:00:00Z"},{"value":"1451649600000000000"},{"value":"6"}],[{"value":"2016-01-01T13:00:00Z"},{"value":"1451653200000000000"},{"value":"7"}],[{"value":"2016-01-01T14:00:00Z"},{"value":"1451656800000000000"},{"value":"8"}],[{"value":"2016-01-01T15:00:00Z"},{"value":"1451660400000000000"},{"value":"9"}],[{"value":"2016-01-01T16:00:00Z"},{"value":"1451664000000000000"},{"value":"10"}],[{"value":"2016-01-01T17:00:00Z"},{"value":"1451667600000000000"},{"value":"11"}],[{"value":"2016-01-01T18:00:00Z"},{"value":"1451671200000000000"},{"value":"12"}],[{"value":"2016-01-01T19:00:00Z"},{"value":"1451674800000000000"},{"value":"13"}],[{"value":"2016-01-01T20:00:00Z"},{"value":"1451678400000000000"},{"value":"14"}],[{"value":"2016-01-01T21:00:00Z"},{"value":"1451682000000000000"},{"value":"15"}],[{"value":"2016-01-01T22:00:00Z"},{"value":"1451685600000000000"},{"value":"16"}],[{"value":"2016-01-01T23:00:00Z"},{"value":"1451689200000000000"},{"value":"17"}],[{"value":"2016-01-02T00:00:00Z"},{"value":"1451692800000000000"},{"value":"18"}],[{"value":"2016-01-02T01:00:00Z"},{"value":"1451696400000000000"},{"value":"19"}],[{"value":"2016-01-02T02:00:00Z"},{"value":"1451700000000000000"},{"value":"20"}],[{"value":"2016-01-02T03:00:00Z"},{"value":"1451703600000000000"},{"value":"21"}],[{"value":"2016-01-02T04:00:00Z"},{"value":"1451707200000000000"},{"value":"22"}],[{"value":"2016-01-02T05:00:00Z"},{"value":"1451710800000000000"},{"value":"23"}],[{"value":"2016-01-02T06:00:00Z"},{"value":"1451714400000000000"},{"value":"24"}],[{"value":"2016-01-02T07:00:00Z"},{"value":"1451718000000000000"},{"value":"25"}],[{"value":"2016-01-02T08:00:00Z"},{"value":"1451721600000000000"},{"value":"26"}],[{"value":"2016-01-02T09:00:00Z"},{"value":"1451725200000000000"},{"value":"27"}],[{"value":"2016-01-02T10:00:00Z"},{"value":"1451728800000000000"},{"value":"28"}],[{"value":"2016-01-02T11:00:00Z"},{"value":"1451732400000000000"},{"value":"29"}],[{"value":"2016-01-02T12:00:00Z"},{"value":"1451736000000000000"},{"value":"30"}],[{"value":"2016-01-02T13:00:00Z"},{"value":"1451739600000000000"},{"value":"31"}],[{"value":"2016-01-02T14:00:00Z"},{"value":"1451743200000000000"},{"value":"32"}],[{"value":"2016-01-02T15:00:00Z"},{"value":"1451746800000000000"},{"value":"33"}],[{"value":"2016-01-02T16:00:00Z"},{"value":"1451750400000000000"},{"value":"34"}],[{"value":"2016-01-02T17:00:00Z"},{"value":"1451754000000000000"},{"value":"35"}],[{"value":"2016-01-02T18:00:00Z"},{"value":"1451757600000000000"},{"value":"36"}],[{"value":"2016-01-02T19:00:00Z"},{"value":"1451761200000000000"},{"value":"37"}],[{"value":"2016-01-02T20:00:00Z"},{"value":"1451764800000000000"},{"value":"38"}],[{"value":"2016-01-02T21:00:00Z"},{"value":"1451768400000000000"},{"value":"39"}],[{"value":"2016-01-02T22:00:00Z"},{"value":"1451772000000000000"},{"value":"40"}],[{"value":"2016-01-02T23:00:00Z"},{"value":"1451775600000000000"},{"value":"41"}],[{"value":"2016-01-03T00:00:00Z"},{"value":"1451779200000000000"},{"value":"42"}],[{"value":"2016-01-03T01:00:00Z"},{"value":"1451782800000000000"},{"value":"43"}],[{"value":"2016-01-03T02:00:00Z"},{"value":"1451786400000000000"},{"value":"44"}],[{"value":"2016-01-03T03:00:00Z"},{"value":"1451790000000000000"},{"value":"45"}],[{"value":"2016-01-03T04:00:00Z"},{"value":"1451793600000000000"},{"value":"46"}],[{"value":"2016-01-03T05:00:00Z"},{"value":"1451797200000000000"},{"value":"47"}],[{"value":"2016-01-03T06:00:00Z"},{"value":"1451800800000000000"},{"value":"48"}],[{"value":"2016-01-03T07:00:00Z"},{"value":"1451804400000000000"},{"value":"49"}],[{"value":"2016-01-03T08:00:00Z"},{"value":"1451808000000000000"},{"value":"50"}],[{"value":"2016-01-03T09:00:00Z"},{"value":"1451811600000000000"},{"value":"51"}],[{"value":"2016-01-03T10:00:00Z"},{"value":"1451815200000000000"},{"value":"52"}],[{"value":"2016-01-03T11:00:00Z"},{"value":"1451818800000000000"},{"value":"53"}],[{"value":"2016-01-03T12:00:00Z"},{"value":"1451822400000000000"},{"value":"54"}],[{"value":"2016-01-03T13:00:00Z"},{"value":"1451826000000000000"},{"value":"55"}],[{"value":"2016-01-03T14:00:00Z"},{"value":"1451829600000000000"},{"value":"56"}],[{"value":"2016-01-03T15:00:00Z"},{"value":"1451833200000000000"},{"value":"57"}],[{"value":"2016-01-03T16:00:00Z"},{"value":"1451836800000000000"},{"value":"58"}],[{"value":"2016-01-03T17:00:00Z"},{"value":"1451840400000000000"},{"value":"59"}],[{"value":"2016-01-03T18:00:00Z"},{"value":"1451844000000000000"},{"value":"60"}],[{"value":"2016-01-03T19:00:00Z"},{"value":"1451847600000000000"},{"value":"61"}],[{"value":"2016-01-03T20:00:00Z"},{"value":"1451851200000000000"},{"value":"62"}],[{"value":"2016-01-03T21:00:00Z"},{"value":"1451854800000000000"},{"value":"63"}],[{"value":"2016-01-03T22:00:00Z"},{"value":"1451858400000000000"},{"value":"64"}],[{"value":"2016-01-03T23:00:00Z"},{"value":"1451862000000000000"},{"value":"65"}],[{"value":"2016-01-04T00:00:00Z"},{"value":"1451865600000000000"},{"value":"66"}],[{"value":"2016-01-04T01:00:00Z"},{"value":"1451869200000000000"},{"value":"67"}],[{"value":"2016-01-04T02:00:00Z"},{"value":"1451872800000000000"},{"value":"68"}],[{"value":"2016-01-04T03:00:00Z"},{"value":"1451876400000000000"},{"value":"69"}],[{"value":"2016-01-04T04:00:00Z"},{"value":"1451880000000000000"},{"value":"70"}],[{"value":"2016-01-04T05:00:00Z"},{"value":"1451883600000000000"},{"value":"71"}],[{"value":"2016-01-04T06:00:00Z"},{"value":"1451887200000000000"},{"value":"72"}],[{"value":"2016-01-04T07:00:00Z"},{"value":"1451890800000000000"},{"value":"73"}],[{"value":"2016-01-04T08:00:00Z"},{"value":"1451894400000000000"},{"value":"74"}],[{"value":"2016-01-04T09:00:00Z"},{"value":"1451898000000000000"},{"value":"75"}],[{"value":"2016-01-04T10:00:00Z"},{"value":"1451901600000000000"},{"value":"76"}],[{"value":"2016-01-04T11:00:00Z"},{"value":"1451905200000000000"},{"value":"77"}],[{"value":"2016-01-04T12:00:00Z"},{"value":"1451908800000000000"},{"value":"78"}],[{"value":"2016-01-04T13:00:00Z"},{"value":"1451912400000000000"},{"value":"79"}],[{"value":"2016-01-04T14:00:00Z"},{"value":"1451916000000000000"},{"value":"80"}],[{"value":"2016-01-04T15:00:00Z"},{"value":"1451919600000000000"},{"value":"81"}],[{"value":"2016-01-04T16:00:00Z"},{"value":"1451923200000000000"},{"value":"82"}],[{"value":"2016-01-04T17:00:00Z"},{"value":"1451926800000000000"},{"value":"83"}],[{"value":"2016-01-04T18:00:00Z"},{"value":"1451930400000000000"},{"value":"84"}],[{"value":"2016-01-04T19:00:00Z"},{"value":"1451934000000000000"},{"value":"85"}],[{"value":"2016-01-04T20:00:00Z"},{"value":"1451937600000000000"},{"value":"86"}],[{"value":"2016-01-04T21:00:00Z"},{"value":"1451941200000000000"},{"value":"87"}],[{"value":"2016-01-04T22:00:00Z"},{"value":"1451944800000000000"},{"value":"88"}],[{"value":"2016-01-04T23:00:00Z"},{"value":"1451948400000000000"},{"value":"89"}],[{"value":"2016-01-05T00:00:00Z"},{"value":"1451952000000000000"},{"value":"90"}],[{"value":"2016-01-05T01:00:00Z"},{"value":"1451955600000000000"},{"value":"91"}],[{"value":"2016-01-05T02:00:00Z"},{"value":"1451959200000000000"},{"value":"92"}],[{"value":"2016-01-05T03:00:00Z"},{"value":"1451962800000000000"},{"value":"93"}],[{"value":"2016-01-05T04:00:00Z"},{"value":"1451966400000000000"},{"value":"94"}],[{"value":"2016-01-05T05:00:00Z"},{"value":"1451970000000000000"},{"value":"95"}],[{"value":"2016-01-05T06:00:00Z"},{"value":"1451973600000000000"},{"value":"96"}],[{"value":"2016-01-05T07:00:00Z"},{"value":"1451977200000000000"},{"value":"97"}],[{"value":"2016-01-05T08:00:00Z"},{"value":"1451980800000000000"},{"value":"98"}],[{"value":"2016-01-05T09:00:00Z"},{"value":"1451984400000000000"},{"value":"99"}]]}}}}